kreuzberg/__init__.py
kreuzberg/__main__.py
kreuzberg/_deprecation.py
kreuzberg/_internal_bindings.abi3.so
kreuzberg/_setup_lib_path.py
kreuzberg/exceptions.py
kreuzberg/py.typed
kreuzberg/types.py
kreuzberg/ocr/__init__.py
kreuzberg/ocr/easyocr.py
kreuzberg/ocr/paddleocr.py
kreuzberg/ocr/protocol.py
kreuzberg/postprocessors/__init__.py
kreuzberg/postprocessors/protocol.py
kreuzberg-4.2.6.dist-info/METADATA
kreuzberg-4.2.6.dist-info/WHEEL
kreuzberg-4.2.6.dist-info/entry_points.txt
kreuzberg-4.2.6.dist-info/RECORD
