Metadata-Version: 2.4
Name: kreuzberg
Version: 4.2.6
Classifier: Development Status :: 4 - Beta
Classifier: Intended Audience :: Developers
Classifier: Intended Audience :: Information Technology
Classifier: Intended Audience :: Science/Research
Classifier: License :: OSI Approved :: MIT License
Classifier: Operating System :: OS Independent
Classifier: Programming Language :: Python :: 3 :: Only
Classifier: Programming Language :: Python :: 3.10
Classifier: Programming Language :: Python :: 3.11
Classifier: Programming Language :: Python :: 3.12
Classifier: Programming Language :: Python :: 3.13
Classifier: Programming Language :: Python :: 3.14
Classifier: Programming Language :: Python :: Implementation :: CPython
Classifier: Programming Language :: Rust
Classifier: Topic :: Office/Business
Classifier: Topic :: Scientific/Engineering :: Information Analysis
Classifier: Topic :: Software Development :: Libraries :: Python Modules
Classifier: Topic :: Text Processing
Classifier: Topic :: Text Processing :: Filters
Classifier: Topic :: Text Processing :: General
Classifier: Typing :: Typed
Requires-Dist: kreuzberg[easyocr,paddleocr] ; extra == 'all'
Requires-Dist: easyocr>=1.7.2 ; python_full_version < '3.14' and extra == 'easyocr'
Requires-Dist: torch>=2.9.1 ; python_full_version < '3.14' and extra == 'easyocr'
Requires-Dist: paddleocr>=3.3.2 ; python_full_version < '3.14' and extra == 'paddleocr'
Requires-Dist: paddlepaddle>=3.2.1,<3.2.2 ; python_full_version < '3.14' and extra == 'paddleocr'
Requires-Dist: setuptools>=80.9 ; python_full_version < '3.14' and extra == 'paddleocr'
Provides-Extra: all
Provides-Extra: easyocr
Provides-Extra: paddleocr
Summary: High-performance document intelligence library for Python. Extract text, metadata, and structured data from PDFs, Office documents, images, and 50+ formats. Powered by Rust core for 10-50x speed improvements.
Keywords: document-extraction,document-intelligence,document-parsing,document-processing,docx,easyocr,email-parsing,html,markdown,metadata-extraction,ocr,office-documents,paddleocr,pdf,pdf-extraction,performance,pptx,rust,table-extraction,tesseract,text-extraction,xlsx,xml
Home-Page: https://goldziher.github.io/kreuzberg/
Author-email: Na'aman Hirschfeld <nhirschfeld@gmail.com>
Maintainer-email: Na'aman Hirschfeld <nhirschfeld@gmail.com>
License: MIT
Requires-Python: >=3.10
Project-URL: Changelog, https://kreuzberg.dev/CHANGELOG/
Project-URL: Documentation, https://kreuzberg.dev
Project-URL: Homepage, https://kreuzberg.dev
Project-URL: Issues, https://github.com/kreuzberg-dev/kreuzberg/issues
Project-URL: Repository, https://github.com/kreuzberg-dev/kreuzberg
Project-URL: Source, https://github.com/kreuzberg-dev/kreuzberg
